jam/__init__.py
jam/common.py
jam/dataset.py
jam/events.py
jam/filelock.py
jam/items.py
jam/keywords.py
jam/langs.py
jam/langs.sqlite
jam/report.py
jam/tree.py
jam/wsgi.py
jam/wsgi_server.py
jam/admin/__init__.py
jam/admin/admin.py
jam/admin/builder.py
jam/admin/builder_structure.info
jam/admin/copy_db.py
jam/admin/export_metadata.py
jam/admin/import_metadata.py
jam/admin/task.py
jam/admin/upgrade.py
jam/css/admin.css
jam/css/admin.min.css
jam/css/bootstrap-amelia.css
jam/css/bootstrap-amelia.min.css
jam/css/bootstrap-cerulean.css
jam/css/bootstrap-cerulean.min.css
jam/css/bootstrap-cosmo.css
jam/css/bootstrap-cosmo.min.css
jam/css/bootstrap-flatly.css
jam/css/bootstrap-flatly.min.css
jam/css/bootstrap-journal.css
jam/css/bootstrap-journal.min.css
jam/css/bootstrap-modal.css
jam/css/bootstrap-modal.min.css
jam/css/bootstrap-readable.css
jam/css/bootstrap-readable.min.css
jam/css/bootstrap-responsive.css
jam/css/bootstrap-responsive.min.css
jam/css/bootstrap-slate.css
jam/css/bootstrap-slate.min.css
jam/css/bootstrap-spacelab.css
jam/css/bootstrap-spacelab.min.css
jam/css/bootstrap-united.css
jam/css/bootstrap-united.min.css
jam/css/bootstrap.css
jam/css/bootstrap.min.css
jam/css/datepicker.css
jam/css/datepicker.min.css
jam/css/jam.css
jam/css/jam.min.css
jam/css/jam12.css
jam/css/jam12.min.css
jam/css/bs5/bootstrap-cerulean.css
jam/css/bs5/bootstrap-cerulean.min.css
jam/css/bs5/bootstrap-cosmo.css
jam/css/bs5/bootstrap-cosmo.min.css
jam/css/bs5/bootstrap-darkly.css
jam/css/bs5/bootstrap-darkly.min.css
jam/css/bs5/bootstrap-flatly.css
jam/css/bs5/bootstrap-flatly.min.css
jam/css/bs5/bootstrap-icons.css
jam/css/bs5/bootstrap-icons.min.css
jam/css/bs5/bootstrap-icons.scss
jam/css/bs5/bootstrap-journal.css
jam/css/bs5/bootstrap-journal.min.css
jam/css/bs5/bootstrap-materia.css
jam/css/bs5/bootstrap-materia.min.css
jam/css/bs5/bootstrap-morph.css
jam/css/bs5/bootstrap-morph.min.css
jam/css/bs5/bootstrap-quartz.css
jam/css/bs5/bootstrap-quartz.min.css
jam_py_v7-7.0.86.dist-info/licenses/AUTHORS
jam_py_v7-7.0.86.dist-info/licenses/LICENSE
jam_py_v7-7.0.86.dist-info/METADATA
jam_py_v7-7.0.86.dist-info/WHEEL
jam_py_v7-7.0.86.dist-info/top_level.txt
jam_py_v7-7.0.86.dist-info/RECORD
