Metadata-Version: 2.4
Name: jam.py-v7
Version: 7.0.86
Summary: Jam.py Application Builder is an event-driven framework         for the development of web database applications.
Home-page: https://github.com/jam-py-v5/jam-py
Author: Andrew Yushev
Author-email: yushevaa@gmail.com
License: BSD
Classifier: Development Status :: 2 - Pre-Alpha
Classifier: Environment :: Web Environment
Classifier: Intended Audience :: Developers
Classifier: License :: OSI Approved :: BSD License
Classifier: Operating System :: OS Independent
Classifier: Programming Language :: Python
Classifier: Programming Language :: JavaScript
Classifier: Topic :: Internet :: WWW/HTTP
Classifier: Topic :: Internet :: WWW/HTTP :: Dynamic Content
Classifier: Topic :: Software Development :: Libraries :: Application Frameworks
Classifier: Topic :: Software Development :: Libraries :: Python Modules
Classifier: Topic :: Database
Classifier: Topic :: Database :: Front-Ends
Requires-Python: >= 3.7
License-File: LICENSE
License-File: AUTHORS
Requires-Dist: Werkzeug>=3.0.0
Requires-Dist: sqlalchemy
Requires-Dist: esprima
Requires-Dist: pyjsparser
Requires-Dist: jsmin
Requires-Dist: sqlparse
Requires-Dist: standard-imghdr
Dynamic: author
Dynamic: author-email
Dynamic: classifier
Dynamic: description
Dynamic: description-content-type
Dynamic: home-page
Dynamic: license
Dynamic: license-file
Dynamic: requires-dist
Dynamic: requires-python
Dynamic: summary
